{
  "mode": "hiragana_food",
  "reels": [
    {
      "id": "left",
      "cells": ["ま", "ぶ", "す", "ま", "う", "ぶ", "み", "う", "い", "み", "と", "い", "と", "ま", "い", "さ", "す", "う", "み", "さ", "と"]
    },
    {
      "id": "middle",
      "cells": ["う", "ぐ", "ど", "か", "し", "な", "ぐ", "ん", "か", "ん", "ち", "ぐ", "う", "ど", "し", "な", "か", "ち", "ん", "ち", "な"]
    },
    {
      "id": "right",
      "cells": ["や", "ん", "ご", "こ", "ま", "う", "ま", "ご", "ぎ", "ん", "ふ", "や", "ろ", "ふ", "ま", "ろ", "こ", "ご", "う", "ろ", "ぎ"]
    }
  ]
}
