{
  "mode": "security",
  "reels": [
    {
      "id": "left",
      "cells": ["ハ", "パ", "ワ", "ト", "ス", "ボ", "リ", "ピ", "ポ", "ホ", "ハ", "パ", "ワ", "ト", "ス", "ボ", "リ", "ピ", "ポ", "ホ", "シ"]
    },
    {
      "id": "middle",
      "cells": ["ッ", "ア", "ー", "ロ", "ッ", "パ", "ス", "ッ", "ン", "ー", "ス", "ッ", "パ", "ロ", "ッ", "ス", "ー", "ン", "パ", "ェ", "イ"]
    },
    {
      "id": "right",
      "cells": ["ク", "ア", "チ", "ム", "イ", "ト", "ク", "グ", "ト", "ム", "ル", "ク", "チ", "ム", "イ", "ト", "グ", "ト", "ル", "オ", "ウ"]
    }
  ]
}
